django_seo_audit/__init__.py
django_seo_audit/apps.py
django_seo_audit/core.py
django_seo_audit/mixins.py
django_seo_audit/protocols.py
django_seo_audit/registry.py
django_seo_audit/management/__init__.py
django_seo_audit/management/commands/__init__.py
django_seo_audit/management/commands/seo_audit.py
django_seo_audit/rules/__init__.py
django_seo_audit/rules/content_rules.py
django_seo_audit/rules/core_seo_rules.py
django_seo_audit/rules/social_media_rules.py
django_seo_audit/rules/technical_seo_rules.py
django_seo_audit-0.2.0.dist-info/METADATA
django_seo_audit-0.2.0.dist-info/WHEEL
django_seo_audit-0.2.0.dist-info/licenses/LICENSE
django_seo_audit-0.2.0.dist-info/RECORD
